claudefig/__init__.py
claudefig/__main__.py
claudefig/_version.py
claudefig/component_loaders.py
claudefig/config.py
claudefig/config_template_manager.py
claudefig/error_messages.py
claudefig/exceptions.py
claudefig/initializer.py
claudefig/logging_config.py
claudefig/models.py
claudefig/preset_manager.py
claudefig/preset_validator.py
claudefig/template_manager.py
claudefig/user_config.py
claudefig/cli/__init__.py
claudefig/cli/decorators.py
claudefig/cli/handlers.py
claudefig/cli/main.py
claudefig/cli/types.py
claudefig/cli/commands/__init__.py
claudefig/cli/commands/components.py
claudefig/cli/commands/config.py
claudefig/cli/commands/files.py
claudefig/cli/commands/presets.py
claudefig/repositories/__init__.py
claudefig/repositories/base.py
claudefig/repositories/config_repository.py
claudefig/repositories/preset_repository.py
claudefig/services/__init__.py
claudefig/services/component_discovery_service.py
claudefig/services/config_service.py
claudefig/services/file_instance_service.py
claudefig/services/preset_definition_loader.py
claudefig/services/preset_service.py
claudefig/services/structure_validator.py
claudefig/services/validation_service.py
claudefig/tui/__init__.py
claudefig/tui/app.py
claudefig/tui/base/__init__.py
claudefig/tui/base/mixins.py
claudefig/tui/base/modal_screen.py
claudefig/tui/base/navigation.py
claudefig/tui/panels/__init__.py
claudefig/tui/panels/config_panel.py
claudefig/tui/panels/content_panel.py
claudefig/tui/panels/initialize_panel.py
claudefig/tui/panels/presets_panel.py
claudefig/tui/screens/__init__.py
claudefig/tui/screens/apply_preset.py
claudefig/tui/screens/create_preset.py
claudefig/tui/screens/create_preset_wizard.py
claudefig/tui/screens/delete_preset.py
claudefig/tui/screens/file_instances.py
claudefig/tui/screens/general_config.py
claudefig/tui/screens/overview.py
claudefig/tui/screens/preset_details.py
claudefig/tui/screens/project_settings.py
claudefig/tui/screens/save_component.py
claudefig/tui/styles/base.tcss
claudefig-1.0.1.dist-info/METADATA
claudefig-1.0.1.dist-info/WHEEL
claudefig-1.0.1.dist-info/entry_points.txt
claudefig-1.0.1.dist-info/licenses/LICENSE
claudefig-1.0.1.dist-info/RECORD
