Metadata-Version: 2.4
Name: claudefig
Version: 1.0.1
Summary: Universal config CLI tool for setting up Claude Code repositories
Project-URL: Homepage, https://github.com/robmcdonald5/claudefig
Project-URL: Documentation, https://github.com/robmcdonald5/claudefig#readme
Project-URL: Repository, https://github.com/robmcdonald5/claudefig
Project-URL: Changelog, https://github.com/robmcdonald5/claudefig/blob/main/CHANGELOG.md
Project-URL: Issues, https://github.com/robmcdonald5/claudefig/issues
Author-email: Joshua McDonald <joshua@joshuamcdonald.me>
License: MIT
License-File: LICENSE
Keywords: claude,claude-code,cli,configuration,repo-setup
Classifier: Development Status :: 4 - Beta
Classifier: Intended Audience :: Developers
Classifier: License :: OSI Approved :: MIT License
Classifier: Operating System :: OS Independent
Classifier: Programming Language :: Python :: 3
Classifier: Programming Language :: Python :: 3.10
Classifier: Programming Language :: Python :: 3.11
Classifier: Programming Language :: Python :: 3.12
Classifier: Programming Language :: Python :: 3.13
Classifier: Topic :: Software Development :: Libraries :: Python Modules
Classifier: Topic :: Utilities
Requires-Python: >=3.10
Requires-Dist: click<9.0,>=8.0
Requires-Dist: platformdirs<5.0,>=4.0
Requires-Dist: rich<15.0,>=13.0
Requires-Dist: textual>=0.47.0
Requires-Dist: tomli-w>=1.0
Requires-Dist: tomli>=2.0; python_version < '3.11'
Provides-Extra: dev
Requires-Dist: factory-boy>=3.3.0; extra == 'dev'
Requires-Dist: hypothesis>=6.92; extra == 'dev'
Requires-Dist: mypy>=1.0; extra == 'dev'
Requires-Dist: pre-commit>=3.0; extra == 'dev'
Requires-Dist: pytest-asyncio>=0.21.0; extra == 'dev'
Requires-Dist: pytest-benchmark>=4.0; extra == 'dev'
Requires-Dist: pytest-cov>=4.0; extra == 'dev'
Requires-Dist: pytest-factoryboy>=2.6.0; extra == 'dev'
Requires-Dist: pytest>=7.0; extra == 'dev'
Requires-Dist: ruff>=0.1.0; extra == 'dev'
Requires-Dist: tox>=4.0; extra == 'dev'
